{
    "female_1465.wav": [
        1.0,
        1.0,
        0.9911623001098633
    ],
    "female_1400.wav": [
        1.0,
        1.0,
        0.7249795198440552
    ],
    "male_1942.wav": [
        0.0,
        0.0,
        0.0019627315923571587
    ],
    "female_1501.wav": [
        1.0,
        1.0,
        0.9937639832496643
    ],
    "male_3059.wav": [
        0.0,
        0.0,
        0.002993089146912098
    ],
    "male_3068.wav": [
        0.0,
        0.0,
        6.756635684723733e-06
    ],
    "female_836.wav": [
        1.0,
        1.0,
        0.9031067490577698
    ],
    "male_1734.wav": [
        0.0,
        0.0,
        0.0001417480525560677
    ],
    "male_2616.wav": [
        0.0,
        0.0,
        0.03801414370536804
    ],
    "male_504.wav": [
        0.0,
        0.0,
        0.00022247637389227748
    ],
    "female_1401.wav": [
        1.0,
        1.0,
        0.9662423729896545
    ],
    "male_3291.wav": [
        0.0,
        0.0,
        7.39455799703137e-07
    ],
    "female_705.wav": [
        1.0,
        1.0,
        0.9999992847442627
    ],
    "female_1189.wav": [
        1.0,
        1.0,
        0.8052876591682434
    ],
    "male_1797.wav": [
        0.0,
        0.0,
        2.761165887932293e-05
    ],
    "female_110.wav": [
        1.0,
        1.0,
        0.9972071051597595
    ],
    "male_3086.wav": [
        0.0,
        0.0,
        0.008473035879433155
    ],
    "male_1598.wav": [
        0.0,
        0.0,
        0.018671948462724686
    ],
    "female_6.wav": [
        1.0,
        1.0,
        0.9934741854667664
    ],
    "male_1278.wav": [
        0.0,
        0.0,
        0.023585472255945206
    ],
    "male_2619.wav": [
        0.0,
        0.0,
        0.11322660744190216
    ],
    "female_288.wav": [
        1.0,
        1.0,
        0.8396357893943787
    ],
    "male_488.wav": [
        0.0,
        0.0,
        0.1459859013557434
    ],
    "male_781.wav": [
        0.0,
        0.0,
        0.02500416338443756
    ],
    "female_879.wav": [
        0.0,
        1.0,
        0.41951984167099
    ],
    "male_791.wav": [
        0.0,
        0.0,
        0.028167715296149254
    ],
    "male_3538.wav": [
        0.0,
        0.0,
        0.00020146140013821423
    ],
    "male_27.wav": [
        0.0,
        0.0,
        2.1117435608175583e-05
    ],
    "male_277.wav": [
        0.0,
        0.0,
        0.03496142104268074
    ],
    "male_1679.wav": [
        0.0,
        0.0,
        0.0691576674580574
    ],
    "male_165.wav": [
        0.0,
        0.0,
        0.005050241947174072
    ],
    "female_259.wav": [
        1.0,
        1.0,
        0.9959872364997864
    ],
    "female_1903.wav": [
        1.0,
        1.0,
        0.9939665794372559
    ],
    "female_1899.wav": [
        1.0,
        1.0,
        0.8659191131591797
    ],
    "male_2317.wav": [
        0.0,
        0.0,
        0.00026325162616558373
    ],
    "male_1579.wav": [
        0.0,
        0.0,
        0.007805376313626766
    ],
    "female_652.wav": [
        1.0,
        1.0,
        0.9577908515930176
    ],
    "male_496.wav": [
        0.0,
        0.0,
        0.01215605903416872
    ],
    "female_1830.wav": [
        0.0,
        1.0,
        0.49799782037734985
    ],
    "female_1867.wav": [
        1.0,
        1.0,
        0.7813618183135986
    ],
    "female_2148.wav": [
        0.0,
        1.0,
        0.3669668436050415
    ],
    "male_1090.wav": [
        0.0,
        0.0,
        0.003320734016597271
    ],
    "male_2877.wav": [
        0.0,
        0.0,
        4.946192802890437e-06
    ],
    "female_2128.wav": [
        1.0,
        1.0,
        0.8875946402549744
    ],
    "male_569.wav": [
        0.0,
        0.0,
        2.670405194749037e-07
    ],
    "male_3448.wav": [
        0.0,
        0.0,
        0.00021778870723210275
    ],
    "female_1924.wav": [
        1.0,
        1.0,
        0.8862180113792419
    ],
    "male_1069.wav": [
        0.0,
        0.0,
        0.0004475850146263838
    ],
    "male_2891.wav": [
        0.0,
        0.0,
        0.00019259974942542613
    ],
    "male_1927.wav": [
        0.0,
        0.0,
        0.01193039771169424
    ],
    "male_1091.wav": [
        0.0,
        0.0,
        0.002567665185779333
    ],
    "female_1377.wav": [
        1.0,
        1.0,
        0.9952119588851929
    ],
    "female_87.wav": [
        1.0,
        1.0,
        0.9929085969924927
    ],
    "male_2077.wav": [
        0.0,
        0.0,
        0.010475801303982735
    ],
    "female_2089.wav": [
        1.0,
        1.0,
        0.6782376170158386
    ],
    "female_106.wav": [
        1.0,
        1.0,
        0.9329620599746704
    ],
    "female_958.wav": [
        0.0,
        1.0,
        0.4935733675956726
    ],
    "female_1861.wav": [
        0.0,
        1.0,
        0.4041101932525635
    ],
    "male_1281.wav": [
        0.0,
        0.0,
        0.00023664247419219464
    ],
    "female_320.wav": [
        0.0,
        1.0,
        0.2235560268163681
    ],
    "male_1322.wav": [
        0.0,
        0.0,
        0.14582158625125885
    ],
    "female_2297.wav": [
        1.0,
        1.0,
        0.9284096360206604
    ],
    "male_3117.wav": [
        0.0,
        0.0,
        0.03303336724638939
    ],
    "female_787.wav": [
        1.0,
        1.0,
        0.9672036170959473
    ],
    "female_1096.wav": [
        1.0,
        1.0,
        0.9299262166023254
    ],
    "male_1890.wav": [
        0.0,
        0.0,
        0.021432016044855118
    ],
    "male_295.wav": [
        0.0,
        0.0,
        0.0010033934377133846
    ],
    "male_3451.wav": [
        0.0,
        0.0,
        0.0016302189324051142
    ],
    "male_902.wav": [
        0.0,
        0.0,
        0.005653629079461098
    ],
    "female_629.wav": [
        1.0,
        1.0,
        0.8762394189834595
    ],
    "male_1318.wav": [
        0.0,
        0.0,
        0.0004543011891655624
    ],
    "female_1368.wav": [
        1.0,
        1.0,
        0.9998284578323364
    ],
    "female_27.wav": [
        0.0,
        1.0,
        0.062373001128435135
    ],
    "male_1904.wav": [
        0.0,
        0.0,
        0.0011983310105279088
    ],
    "male_2076.wav": [
        1.0,
        0.0,
        0.7047183513641357
    ],
    "male_1618.wav": [
        0.0,
        0.0,
        0.008714810945093632
    ],
    "female_1488.wav": [
        1.0,
        1.0,
        0.7483614683151245
    ],
    "male_3616.wav": [
        0.0,
        0.0,
        7.0099458753247745e-06
    ],
    "female_79.wav": [
        1.0,
        1.0,
        0.968636155128479
    ],
    "male_371.wav": [
        0.0,
        0.0,
        0.009664062410593033
    ],
    "male_1795.wav": [
        0.0,
        0.0,
        0.0006585103692486882
    ],
    "female_310.wav": [
        1.0,
        1.0,
        0.943263590335846
    ],
    "male_2530.wav": [
        0.0,
        0.0,
        0.002754892222583294
    ],
    "female_1124.wav": [
        1.0,
        1.0,
        0.976619303226471
    ],
    "male_3565.wav": [
        0.0,
        0.0,
        0.0002175693225581199
    ],
    "male_2471.wav": [
        0.0,
        0.0,
        0.0005916990339756012
    ],
    "male_1576.wav": [
        0.0,
        0.0,
        1.063847139448626e-05
    ],
    "female_2293.wav": [
        1.0,
        1.0,
        0.9001672267913818
    ],
    "male_534.wav": [
        0.0,
        0.0,
        0.0008143395534716547
    ],
    "male_2067.wav": [
        1.0,
        0.0,
        0.984494149684906
    ],
    "male_3340.wav": [
        0.0,
        0.0,
        0.00019965811225119978
    ],
    "male_681.wav": [
        0.0,
        0.0,
        0.013989675790071487
    ],
    "female_1262.wav": [
        0.0,
        1.0,
        0.3448706567287445
    ],
    "male_1237.wav": [
        0.0,
        0.0,
        0.02189601957798004
    ],
    "female_158.wav": [
        1.0,
        1.0,
        0.9759790301322937
    ],
    "male_2851.wav": [
        0.0,
        0.0,
        1.9448350485617993e-06
    ],
    "male_2187.wav": [
        0.0,
        0.0,
        0.00033526893821544945
    ],
    "male_3650.wav": [
        0.0,
        0.0,
        0.00046247176942415535
    ],
    "male_2709.wav": [
        0.0,
        0.0,
        1.2805768164980691e-05
    ],
    "female_1292.wav": [
        1.0,
        1.0,
        0.9143526554107666
    ],
    "male_743.wav": [
        0.0,
        0.0,
        0.006604186724871397
    ],
    "female_1915.wav": [
        0.0,
        1.0,
        0.023591378703713417
    ],
    "female_2120.wav": [
        1.0,
        1.0,
        0.9911222457885742
    ],
    "female_567.wav": [
        1.0,
        1.0,
        0.999976396560669
    ],
    "male_1766.wav": [
        0.0,
        0.0,
        0.0016167131252586842
    ],
    "female_41.wav": [
        1.0,
        1.0,
        0.9045705199241638
    ],
    "male_2419.wav": [
        0.0,
        0.0,
        0.0033612442202866077
    ],
    "male_67.wav": [
        0.0,
        0.0,
        0.01084220316261053
    ],
    "male_2655.wav": [
        0.0,
        0.0,
        0.008441873826086521
    ],
    "male_2453.wav": [
        0.0,
        0.0,
        2.225334355898667e-06
    ],
    "female_1636.wav": [
        1.0,
        1.0,
        0.9847715497016907
    ],
    "male_1543.wav": [
        0.0,
        0.0,
        0.0156342014670372
    ],
    "female_1847.wav": [
        0.0,
        1.0,
        0.2149643748998642
    ],
    "female_602.wav": [
        1.0,
        1.0,
        0.9823760390281677
    ],
    "female_2296.wav": [
        1.0,
        1.0,
        0.9479992985725403
    ],
    "male_2988.wav": [
        0.0,
        0.0,
        0.0007696218672208488
    ],
    "female_1086.wav": [
        1.0,
        1.0,
        0.9861240386962891
    ],
    "male_794.wav": [
        0.0,
        0.0,
        0.005867120809853077
    ],
    "female_1987.wav": [
        0.0,
        1.0,
        0.003438878571614623
    ],
    "female_383.wav": [
        1.0,
        1.0,
        0.891361653804779
    ],
    "male_843.wav": [
        0.0,
        0.0,
        8.944370347307995e-05
    ],
    "male_971.wav": [
        0.0,
        0.0,
        0.006522239651530981
    ],
    "female_2258.wav": [
        0.0,
        1.0,
        0.19242152571678162
    ],
    "male_1849.wav": [
        0.0,
        0.0,
        0.0015585627406835556
    ],
    "male_3129.wav": [
        0.0,
        0.0,
        5.320288920529492e-08
    ],
    "male_1911.wav": [
        0.0,
        0.0,
        0.0052118003368377686
    ],
    "male_194.wav": [
        0.0,
        0.0,
        0.013590099290013313
    ],
    "male_3390.wav": [
        0.0,
        0.0,
        0.0063496739603579044
    ],
    "male_1337.wav": [
        0.0,
        0.0,
        0.0017080577090382576
    ],
    "male_1761.wav": [
        0.0,
        0.0,
        0.0034857341088354588
    ],
    "male_1545.wav": [
        0.0,
        0.0,
        0.0019215488573536277
    ],
    "male_651.wav": [
        0.0,
        0.0,
        0.003953957464545965
    ],
    "male_3025.wav": [
        0.0,
        0.0,
        0.0006086247158236802
    ],
    "male_520.wav": [
        0.0,
        0.0,
        4.6311851065183873e-07
    ],
    "male_945.wav": [
        0.0,
        0.0,
        1.5255224752763752e-05
    ],
    "female_535.wav": [
        1.0,
        1.0,
        0.6919213533401489
    ],
    "male_1839.wav": [
        0.0,
        0.0,
        0.019405832514166832
    ],
    "female_711.wav": [
        1.0,
        1.0,
        0.8931110501289368
    ],
    "female_1772.wav": [
        0.0,
        1.0,
        0.02694135345518589
    ],
    "male_652.wav": [
        0.0,
        0.0,
        0.0006053344695828855
    ],
    "male_173.wav": [
        0.0,
        0.0,
        1.2109924682590645e-05
    ],
    "male_1855.wav": [
        0.0,
        0.0,
        4.863562935497612e-05
    ],
    "female_877.wav": [
        1.0,
        1.0,
        0.8429655432701111
    ],
    "male_2517.wav": [
        0.0,
        0.0,
        2.5364224143231695e-07
    ],
    "male_613.wav": [
        0.0,
        0.0,
        0.003215966047719121
    ],
    "female_1116.wav": [
        1.0,
        1.0,
        0.9962903261184692
    ],
    "female_1139.wav": [
        1.0,
        1.0,
        0.8911224603652954
    ],
    "male_2355.wav": [
        0.0,
        0.0,
        0.04438692331314087
    ],
    "male_626.wav": [
        0.0,
        0.0,
        0.0003690048470161855
    ],
    "female_1730.wav": [
        1.0,
        1.0,
        0.9850620031356812
    ],
    "male_2802.wav": [
        0.0,
        0.0,
        0.006830550730228424
    ],
    "female_1340.wav": [
        1.0,
        1.0,
        0.9744454026222229
    ],
    "female_1574.wav": [
        1.0,
        1.0,
        0.9881629347801208
    ],
    "male_547.wav": [
        0.0,
        0.0,
        3.665925532914116e-06
    ],
    "male_2564.wav": [
        0.0,
        0.0,
        0.441135048866272
    ],
    "female_387.wav": [
        1.0,
        1.0,
        0.9981639981269836
    ],
    "male_3544.wav": [
        0.0,
        0.0,
        0.0006043585017323494
    ],
    "male_2957.wav": [
        0.0,
        0.0,
        3.8688693166477606e-05
    ],
    "female_1733.wav": [
        1.0,
        1.0,
        0.9917141795158386
    ],
    "male_1917.wav": [
        0.0,
        0.0,
        0.020315999165177345
    ],
    "male_1540.wav": [
        0.0,
        0.0,
        4.517734737419232e-07
    ],
    "male_401.wav": [
        0.0,
        0.0,
        0.00036043761065229774
    ],
    "female_77.wav": [
        1.0,
        1.0,
        0.7473211884498596
    ],
    "female_231.wav": [
        1.0,
        1.0,
        0.95037841796875
    ],
    "male_2418.wav": [
        0.0,
        0.0,
        0.0016375863924622536
    ],
    "male_2502.wav": [
        0.0,
        0.0,
        0.23183360695838928
    ],
    "female_2004.wav": [
        1.0,
        1.0,
        0.9988034963607788
    ],
    "female_1404.wav": [
        1.0,
        1.0,
        0.9015201330184937
    ],
    "female_1296.wav": [
        1.0,
        1.0,
        0.9869553446769714
    ],
    "female_1734.wav": [
        1.0,
        1.0,
        0.9197320938110352
    ],
    "female_1890.wav": [
        1.0,
        1.0,
        0.9959696531295776
    ],
    "male_3161.wav": [
        0.0,
        0.0,
        0.000953369599301368
    ],
    "female_1332.wav": [
        1.0,
        1.0,
        0.9817253947257996
    ],
    "male_478.wav": [
        0.0,
        0.0,
        0.0024794151540845633
    ],
    "male_214.wav": [
        0.0,
        0.0,
        7.334067777264863e-05
    ],
    "female_164.wav": [
        1.0,
        1.0,
        0.9276965856552124
    ],
    "female_764.wav": [
        1.0,
        1.0,
        0.9314224720001221
    ],
    "female_2230.wav": [
        1.0,
        1.0,
        0.9528664350509644
    ],
    "male_191.wav": [
        0.0,
        0.0,
        0.06329519301652908
    ],
    "male_3413.wav": [
        0.0,
        0.0,
        0.01158339437097311
    ],
    "male_438.wav": [
        0.0,
        0.0,
        0.001517826458439231
    ],
    "male_2561.wav": [
        0.0,
        0.0,
        0.305765837430954
    ],
    "female_1257.wav": [
        1.0,
        1.0,
        0.9936826229095459
    ],
    "male_3504.wav": [
        0.0,
        0.0,
        0.0002942518622148782
    ],
    "male_3398.wav": [
        0.0,
        0.0,
        0.020083285868167877
    ],
    "male_419.wav": [
        0.0,
        0.0,
        0.0042898026295006275
    ],
    "female_1252.wav": [
        1.0,
        1.0,
        0.9938949942588806
    ],
    "female_418.wav": [
        1.0,
        1.0,
        0.9925998449325562
    ],
    "male_2158.wav": [
        0.0,
        0.0,
        0.0006766887963749468
    ],
    "male_29.wav": [
        0.0,
        0.0,
        0.38743025064468384
    ],
    "female_13.wav": [
        1.0,
        1.0,
        0.9679328203201294
    ],
    "female_2234.wav": [
        0.0,
        1.0,
        0.2557195723056793
    ],
    "female_1040.wav": [
        1.0,
        1.0,
        0.982142984867096
    ],
    "male_1457.wav": [
        0.0,
        0.0,
        0.026111742481589317
    ],
    "male_1697.wav": [
        0.0,
        0.0,
        0.00011231311509618536
    ],
    "female_1508.wav": [
        1.0,
        1.0,
        0.9845784306526184
    ],
    "male_1132.wav": [
        0.0,
        0.0,
        0.002736761001870036
    ],
    "male_2662.wav": [
        0.0,
        0.0,
        0.002350518712773919
    ],
    "male_3673.wav": [
        0.0,
        0.0,
        5.377821435104124e-05
    ],
    "male_811.wav": [
        0.0,
        0.0,
        0.006560360547155142
    ],
    "male_2660.wav": [
        0.0,
        0.0,
        0.011267194524407387
    ],
    "female_80.wav": [
        0.0,
        1.0,
        0.23544077575206757
    ],
    "male_2604.wav": [
        0.0,
        0.0,
        0.0008937899838201702
    ],
    "male_1210.wav": [
        0.0,
        0.0,
        8.236864232458174e-05
    ],
    "male_1186.wav": [
        0.0,
        0.0,
        0.0016680817352607846
    ],
    "male_529.wav": [
        0.0,
        0.0,
        0.007768030744045973
    ],
    "female_1104.wav": [
        1.0,
        1.0,
        0.9418961405754089
    ],
    "male_2676.wav": [
        0.0,
        0.0,
        0.00209375680424273
    ],
    "female_983.wav": [
        1.0,
        1.0,
        0.9492631554603577
    ],
    "male_2340.wav": [
        0.0,
        0.0,
        0.00023971544578671455
    ],
    "male_3664.wav": [
        0.0,
        0.0,
        0.0003452824894338846
    ],
    "female_1897.wav": [
        1.0,
        1.0,
        0.9722065329551697
    ],
    "female_59.wav": [
        1.0,
        1.0,
        0.9856762886047363
    ],
    "male_361.wav": [
        0.0,
        0.0,
        0.290602445602417
    ],
    "male_2170.wav": [
        0.0,
        0.0,
        2.8348099476716015e-06
    ],
    "male_1286.wav": [
        0.0,
        0.0,
        0.005875838454812765
    ],
    "female_893.wav": [
        1.0,
        1.0,
        0.7429162859916687
    ],
    "male_2475.wav": [
        0.0,
        0.0,
        0.0029086358845233917
    ],
    "female_938.wav": [
        1.0,
        1.0,
        0.7902891635894775
    ],
    "female_856.wav": [
        1.0,
        1.0,
        0.9983938336372375
    ],
    "male_1901.wav": [
        0.0,
        0.0,
        0.060179345309734344
    ],
    "male_3305.wav": [
        0.0,
        0.0,
        0.0021845533046871424
    ],
    "female_1052.wav": [
        1.0,
        1.0,
        0.9999397993087769
    ],
    "male_1111.wav": [
        0.0,
        0.0,
        0.00020488868176471442
    ],
    "male_567.wav": [
        0.0,
        0.0,
        0.0031420474406331778
    ],
    "male_3018.wav": [
        0.0,
        0.0,
        0.005721741355955601
    ],
    "female_2067.wav": [
        1.0,
        1.0,
        0.9992683529853821
    ],
    "male_2788.wav": [
        0.0,
        0.0,
        0.004983600694686174
    ],
    "female_70.wav": [
        1.0,
        1.0,
        0.9985881447792053
    ],
    "female_86.wav": [
        1.0,
        1.0,
        0.9927600622177124
    ],
    "female_1497.wav": [
        1.0,
        1.0,
        0.9351134300231934
    ],
    "female_2018.wav": [
        1.0,
        1.0,
        0.9999896287918091
    ],
    "female_821.wav": [
        1.0,
        1.0,
        0.9694119095802307
    ],
    "male_272.wav": [
        0.0,
        0.0,
        1.2482839792937739e-06
    ],
    "female_754.wav": [
        1.0,
        1.0,
        0.9446985125541687
    ],
    "male_3510.wav": [
        0.0,
        0.0,
        0.19124682247638702
    ],
    "male_2320.wav": [
        0.0,
        0.0,
        0.09849748015403748
    ],
    "male_1288.wav": [
        0.0,
        0.0,
        0.05035718157887459
    ],
    "female_870.wav": [
        1.0,
        1.0,
        0.9877772927284241
    ],
    "male_1854.wav": [
        0.0,
        0.0,
        5.330804924597032e-06
    ],
    "female_991.wav": [
        1.0,
        1.0,
        0.9746910333633423
    ],
    "male_2259.wav": [
        0.0,
        0.0,
        0.0002007859875448048
    ],
    "female_1339.wav": [
        1.0,
        1.0,
        0.9567467570304871
    ],
    "male_1658.wav": [
        0.0,
        0.0,
        0.0017475011991336942
    ],
    "female_713.wav": [
        1.0,
        1.0,
        0.9748091697692871
    ],
    "female_1337.wav": [
        1.0,
        1.0,
        0.9806007742881775
    ],
    "male_709.wav": [
        0.0,
        0.0,
        1.8567820006865077e-05
    ],
    "female_1185.wav": [
        1.0,
        1.0,
        0.9665162563323975
    ],
    "female_1527.wav": [
        0.0,
        1.0,
        0.04191647469997406
    ],
    "female_1863.wav": [
        1.0,
        1.0,
        0.9282628893852234
    ],
    "female_2271.wav": [
        1.0,
        1.0,
        0.9992231130599976
    ],
    "male_2385.wav": [
        0.0,
        0.0,
        0.011550525203347206
    ],
    "male_2516.wav": [
        0.0,
        0.0,
        0.003858263371512294
    ],
    "male_1742.wav": [
        0.0,
        0.0,
        0.03338981047272682
    ],
    "female_1562.wav": [
        1.0,
        1.0,
        0.9669828414916992
    ],
    "female_1607.wav": [
        0.0,
        1.0,
        0.23550666868686676
    ],
    "male_156.wav": [
        1.0,
        0.0,
        0.9849846363067627
    ],
    "female_362.wav": [
        1.0,
        1.0,
        0.9733796119689941
    ],
    "female_2154.wav": [
        1.0,
        1.0,
        0.8933892846107483
    ],
    "male_996.wav": [
        0.0,
        0.0,
        0.0006362212589010596
    ],
    "male_3150.wav": [
        0.0,
        0.0,
        0.001437877886928618
    ],
    "male_3614.wav": [
        1.0,
        0.0,
        0.6087405681610107
    ],
    "male_2917.wav": [
        0.0,
        0.0,
        3.552994894562289e-05
    ],
    "male_124.wav": [
        0.0,
        0.0,
        0.04141053929924965
    ],
    "male_1973.wav": [
        0.0,
        0.0,
        4.1451016841165256e-07
    ],
    "female_1593.wav": [
        1.0,
        1.0,
        0.7603704333305359
    ],
    "male_385.wav": [
        0.0,
        0.0,
        1.3074571143079083e-05
    ],
    "female_250.wav": [
        1.0,
        1.0,
        0.7849934697151184
    ],
    "male_3247.wav": [
        0.0,
        0.0,
        0.059765320271253586
    ],
    "female_1042.wav": [
        1.0,
        1.0,
        0.9973688125610352
    ],
    "female_1384.wav": [
        1.0,
        1.0,
        0.9951426982879639
    ],
    "female_2063.wav": [
        1.0,
        1.0,
        0.7475888133049011
    ],
    "male_105.wav": [
        0.0,
        0.0,
        0.0011036746436730027
    ],
    "female_588.wav": [
        1.0,
        1.0,
        0.9454070329666138
    ],
    "female_1071.wav": [
        1.0,
        1.0,
        0.9850959181785583
    ],
    "female_524.wav": [
        1.0,
        1.0,
        0.9675537943840027
    ],
    "male_1602.wav": [
        0.0,
        0.0,
        0.024733027443289757
    ],
    "male_2117.wav": [
        0.0,
        0.0,
        0.0009911909000948071
    ],
    "female_98.wav": [
        1.0,
        1.0,
        0.9987186193466187
    ],
    "male_3368.wav": [
        0.0,
        0.0,
        0.0013157299254089594
    ],
    "male_379.wav": [
        0.0,
        0.0,
        0.005907732527703047
    ],
    "male_2830.wav": [
        0.0,
        0.0,
        0.01200972031801939
    ],
    "male_3472.wav": [
        0.0,
        0.0,
        0.020748140290379524
    ],
    "male_483.wav": [
        0.0,
        0.0,
        7.894064037827775e-05
    ],
    "male_861.wav": [
        0.0,
        0.0,
        0.010106283240020275
    ],
    "male_1361.wav": [
        0.0,
        0.0,
        0.0001796896249288693
    ],
    "female_1385.wav": [
        1.0,
        1.0,
        0.8731599450111389
    ],
    "female_234.wav": [
        1.0,
        1.0,
        0.9996034502983093
    ],
    "female_1795.wav": [
        1.0,
        1.0,
        0.9330033659934998
    ],
    "male_489.wav": [
        0.0,
        0.0,
        0.007728652562946081
    ],
    "male_917.wav": [
        0.0,
        0.0,
        0.03617461398243904
    ],
    "female_1888.wav": [
        1.0,
        1.0,
        0.9618846774101257
    ],
    "male_2893.wav": [
        0.0,
        0.0,
        5.934636283200234e-05
    ],
    "female_1423.wav": [
        0.0,
        1.0,
        0.18579263985157013
    ],
    "female_332.wav": [
        1.0,
        1.0,
        0.7857955694198608
    ],
    "male_3044.wav": [
        0.0,
        0.0,
        0.002695768605917692
    ],
    "female_1109.wav": [
        1.0,
        1.0,
        0.8990448117256165
    ],
    "male_3054.wav": [
        0.0,
        0.0,
        1.0697488505684305e-05
    ],
    "female_346.wav": [
        1.0,
        1.0,
        0.9140980243682861
    ],
    "male_1308.wav": [
        0.0,
        0.0,
        0.0016094751190394163
    ],
    "male_2268.wav": [
        0.0,
        0.0,
        0.009937422350049019
    ],
    "male_2650.wav": [
        0.0,
        0.0,
        3.4585461605729506e-08
    ],
    "male_2069.wav": [
        0.0,
        0.0,
        0.008635890670120716
    ],
    "male_2165.wav": [
        0.0,
        0.0,
        4.158530373388203e-06
    ],
    "male_1652.wav": [
        0.0,
        0.0,
        0.03836849704384804
    ],
    "male_3295.wav": [
        0.0,
        0.0,
        1.3880921301279159e-08
    ],
    "male_85.wav": [
        0.0,
        0.0,
        0.026822876185178757
    ],
    "male_575.wav": [
        0.0,
        0.0,
        0.00014229975931812078
    ],
    "male_2779.wav": [
        0.0,
        0.0,
        5.368824076867895e-06
    ],
    "female_1791.wav": [
        1.0,
        1.0,
        0.9993343949317932
    ],
    "female_774.wav": [
        1.0,
        1.0,
        0.9709577560424805
    ],
    "male_804.wav": [
        0.0,
        0.0,
        1.3770090845355298e-05
    ],
    "male_805.wav": [
        0.0,
        0.0,
        0.009234766475856304
    ],
    "male_512.wav": [
        0.0,
        0.0,
        0.035015445202589035
    ],
    "female_1947.wav": [
        1.0,
        1.0,
        0.9822378754615784
    ],
    "male_1832.wav": [
        0.0,
        0.0,
        4.099070793017745e-05
    ],
    "male_842.wav": [
        0.0,
        0.0,
        0.002051014918833971
    ],
    "male_2407.wav": [
        0.0,
        0.0,
        0.013956070877611637
    ],
    "male_630.wav": [
        0.0,
        0.0,
        0.012191922403872013
    ],
    "male_910.wav": [
        0.0,
        0.0,
        2.2437683583120815e-05
    ],
    "male_3468.wav": [
        0.0,
        0.0,
        0.0028896054718643427
    ],
    "male_1000.wav": [
        0.0,
        0.0,
        0.4891793429851532
    ],
    "male_3232.wav": [
        0.0,
        0.0,
        0.00044701044680550694
    ],
    "male_1561.wav": [
        0.0,
        0.0,
        0.0028092192951589823
    ],
    "female_506.wav": [
        1.0,
        1.0,
        0.8516292572021484
    ],
    "female_2040.wav": [
        1.0,
        1.0,
        0.8022118806838989
    ],
    "male_3139.wav": [
        0.0,
        0.0,
        0.001321757328696549
    ],
    "male_3566.wav": [
        0.0,
        0.0,
        0.04168708994984627
    ],
    "male_2303.wav": [
        0.0,
        0.0,
        0.39165887236595154
    ],
    "male_682.wav": [
        0.0,
        0.0,
        0.0011974895605817437
    ],
    "female_1283.wav": [
        1.0,
        1.0,
        0.70527184009552
    ],
    "male_320.wav": [
        0.0,
        0.0,
        2.27450072998181e-06
    ],
    "male_2403.wav": [
        0.0,
        0.0,
        0.204495370388031
    ],
    "male_2339.wav": [
        0.0,
        0.0,
        0.0009487845236435533
    ],
    "female_699.wav": [
        1.0,
        1.0,
        0.5729241371154785
    ],
    "female_271.wav": [
        1.0,
        1.0,
        0.9662154316902161
    ],
    "male_521.wav": [
        0.0,
        0.0,
        0.0014781871577724814
    ],
    "female_517.wav": [
        1.0,
        1.0,
        0.8232538104057312
    ],
    "male_986.wav": [
        0.0,
        0.0,
        0.004032786004245281
    ],
    "female_1702.wav": [
        1.0,
        1.0,
        0.9949051141738892
    ],
    "male_2472.wav": [
        0.0,
        0.0,
        0.0011511007323861122
    ],
    "male_485.wav": [
        0.0,
        0.0,
        0.2709028720855713
    ],
    "male_2711.wav": [
        0.0,
        0.0,
        0.00013803489855490625
    ],
    "male_416.wav": [
        0.0,
        0.0,
        0.016568802297115326
    ],
    "male_3221.wav": [
        0.0,
        0.0,
        8.48708295961842e-05
    ],
    "male_233.wav": [
        0.0,
        0.0,
        0.001242835191078484
    ],
    "female_2247.wav": [
        1.0,
        1.0,
        0.9725472331047058
    ],
    "male_1277.wav": [
        0.0,
        0.0,
        6.321006367215887e-07
    ],
    "male_422.wav": [
        0.0,
        0.0,
        0.10235864669084549
    ],
    "female_1923.wav": [
        1.0,
        1.0,
        0.9222131967544556
    ],
    "female_1503.wav": [
        1.0,
        1.0,
        0.9980833530426025
    ],
    "male_2241.wav": [
        0.0,
        0.0,
        0.009623562917113304
    ],
    "male_3552.wav": [
        0.0,
        0.0,
        1.2914735634694807e-05
    ],
    "female_25.wav": [
        1.0,
        1.0,
        0.9472382068634033
    ],
    "male_3421.wav": [
        0.0,
        0.0,
        0.014555380679666996
    ],
    "male_171.wav": [
        0.0,
        0.0,
        0.0004573237965814769
    ],
    "female_420.wav": [
        1.0,
        1.0,
        0.8840917348861694
    ],
    "male_3487.wav": [
        0.0,
        0.0,
        2.473939093761146e-05
    ],
    "male_423.wav": [
        0.0,
        0.0,
        0.015252790413796902
    ],
    "female_272.wav": [
        0.0,
        1.0,
        0.4490475654602051
    ],
    "female_945.wav": [
        0.0,
        1.0,
        0.3909836709499359
    ],
    "female_1151.wav": [
        1.0,
        1.0,
        0.9934123158454895
    ],
    "male_2133.wav": [
        0.0,
        0.0,
        0.0009196487371809781
    ],
    "female_1875.wav": [
        1.0,
        1.0,
        0.7900691032409668
    ],
    "female_2205.wav": [
        1.0,
        1.0,
        0.9796534776687622
    ],
    "female_1558.wav": [
        1.0,
        1.0,
        0.875819206237793
    ],
    "male_736.wav": [
        0.0,
        0.0,
        0.25367170572280884
    ],
    "male_2140.wav": [
        0.0,
        0.0,
        3.435385588090867e-05
    ],
    "male_2761.wav": [
        0.0,
        0.0,
        1.701502696960233e-05
    ],
    "male_2809.wav": [
        0.0,
        0.0,
        0.00647369772195816
    ],
    "male_3610.wav": [
        0.0,
        0.0,
        7.013663434918271e-06
    ],
    "male_2338.wav": [
        0.0,
        0.0,
        6.908029718033504e-06
    ],
    "male_3012.wav": [
        0.0,
        0.0,
        0.0007913739536888897
    ],
    "female_2121.wav": [
        1.0,
        1.0,
        0.9159697890281677
    ],
    "male_2817.wav": [
        0.0,
        0.0,
        0.0009777029044926167
    ],
    "female_128.wav": [
        1.0,
        1.0,
        0.9144749045372009
    ],
    "male_2623.wav": [
        0.0,
        0.0,
        0.13468268513679504
    ],
    "male_2207.wav": [
        0.0,
        0.0,
        0.023169470950961113
    ],
    "female_103.wav": [
        1.0,
        1.0,
        0.9936671853065491
    ],
    "male_2203.wav": [
        0.0,
        0.0,
        0.27122873067855835
    ],
    "female_2279.wav": [
        1.0,
        1.0,
        0.9537567496299744
    ],
    "male_799.wav": [
        0.0,
        0.0,
        0.0004316654521971941
    ],
    "male_2787.wav": [
        0.0,
        0.0,
        4.457081013242714e-05
    ],
    "male_1735.wav": [
        0.0,
        0.0,
        0.004448060877621174
    ],
    "male_1015.wav": [
        0.0,
        0.0,
        0.008371561765670776
    ],
    "female_2182.wav": [
        1.0,
        1.0,
        0.9955542683601379
    ],
    "female_174.wav": [
        1.0,
        1.0,
        0.9594829678535461
    ],
    "male_2873.wav": [
        0.0,
        0.0,
        0.0003449368814472109
    ],
    "male_1793.wav": [
        0.0,
        0.0,
        0.011427891440689564
    ],
    "male_1665.wav": [
        0.0,
        0.0,
        0.006495580077171326
    ],
    "female_19.wav": [
        1.0,
        1.0,
        0.9856836199760437
    ],
    "female_1909.wav": [
        1.0,
        1.0,
        0.7695440649986267
    ],
    "female_1686.wav": [
        1.0,
        1.0,
        0.995177149772644
    ],
    "male_1022.wav": [
        0.0,
        0.0,
        0.00012911442900076509
    ],
    "female_884.wav": [
        1.0,
        1.0,
        0.8034854531288147
    ],
    "male_12.wav": [
        0.0,
        0.0,
        0.00018679093045648187
    ],
    "male_338.wav": [
        0.0,
        0.0,
        0.0004899848136119545
    ],
    "female_145.wav": [
        1.0,
        1.0,
        0.9743129014968872
    ],
    "male_1052.wav": [
        0.0,
        0.0,
        0.00011400295625207946
    ],
    "male_3312.wav": [
        0.0,
        0.0,
        0.0023660361766815186
    ],
    "male_1547.wav": [
        0.0,
        0.0,
        0.00022475513105746359
    ],
    "female_1451.wav": [
        1.0,
        1.0,
        0.8968714475631714
    ],
    "male_501.wav": [
        0.0,
        0.0,
        0.0031527080573141575
    ],
    "male_883.wav": [
        0.0,
        0.0,
        0.017782263457775116
    ],
    "male_1489.wav": [
        0.0,
        0.0,
        5.3080395446158946e-05
    ],
    "female_819.wav": [
        1.0,
        1.0,
        0.985285222530365
    ],
    "male_2602.wav": [
        0.0,
        0.0,
        0.028349457308650017
    ],
    "male_1309.wav": [
        0.0,
        0.0,
        0.0019874100107699633
    ],
    "male_2750.wav": [
        0.0,
        0.0,
        0.006433391943573952
    ],
    "male_1084.wav": [
        0.0,
        0.0,
        0.010118842124938965
    ],
    "female_971.wav": [
        1.0,
        1.0,
        0.8264032006263733
    ],
    "male_204.wav": [
        0.0,
        0.0,
        0.0016205358551815152
    ],
    "male_2871.wav": [
        0.0,
        0.0,
        0.0034878612495958805
    ],
    "female_233.wav": [
        1.0,
        1.0,
        0.6763880848884583
    ],
    "male_3638.wav": [
        0.0,
        0.0,
        0.0033831738401204348
    ],
    "female_338.wav": [
        1.0,
        1.0,
        0.9707593321800232
    ],
    "male_2063.wav": [
        0.0,
        0.0,
        8.02198555902578e-05
    ],
    "male_1220.wav": [
        0.0,
        0.0,
        0.00045335551840253174
    ],
    "male_2706.wav": [
        0.0,
        0.0,
        0.0016205874271690845
    ],
    "male_848.wav": [
        0.0,
        0.0,
        0.000585581234190613
    ],
    "male_3665.wav": [
        0.0,
        0.0,
        0.00735598336905241
    ],
    "male_3568.wav": [
        0.0,
        0.0,
        4.992538379156031e-05
    ],
    "male_1572.wav": [
        0.0,
        0.0,
        2.166822196159046e-05
    ],
    "male_2629.wav": [
        0.0,
        0.0,
        0.008964726701378822
    ],
    "male_269.wav": [
        0.0,
        0.0,
        4.9970680265687406e-05
    ],
    "female_198.wav": [
        1.0,
        1.0,
        0.9998032450675964
    ],
    "female_1823.wav": [
        1.0,
        1.0,
        0.8629414439201355
    ],
    "male_920.wav": [
        0.0,
        0.0,
        0.0002490956976544112
    ],
    "male_3497.wav": [
        0.0,
        0.0,
        0.006843446753919125
    ],
    "male_3193.wav": [
        0.0,
        0.0,
        0.0006381252896972001
    ],
    "female_1297.wav": [
        1.0,
        1.0,
        0.6945778131484985
    ],
    "male_723.wav": [
        0.0,
        0.0,
        2.458608378219651e-06
    ],
    "male_1384.wav": [
        0.0,
        0.0,
        0.0012719471706077456
    ],
    "female_972.wav": [
        1.0,
        1.0,
        0.9905765056610107
    ],
    "female_361.wav": [
        1.0,
        1.0,
        0.9239343404769897
    ],
    "female_2283.wav": [
        1.0,
        1.0,
        0.845708429813385
    ],
    "male_381.wav": [
        0.0,
        0.0,
        3.964301140513271e-05
    ],
    "male_2046.wav": [
        0.0,
        0.0,
        1.0690095223253593e-05
    ],
    "female_1405.wav": [
        1.0,
        1.0,
        0.8070203065872192
    ],
    "male_2740.wav": [
        0.0,
        0.0,
        0.0053510949946939945
    ],
    "male_1838.wav": [
        0.0,
        0.0,
        0.00021451638895086944
    ],
    "female_18.wav": [
        1.0,
        1.0,
        0.8817650079727173
    ],
    "female_1102.wav": [
        1.0,
        1.0,
        0.9960362315177917
    ],
    "male_1822.wav": [
        0.0,
        0.0,
        0.0006026610499247909
    ],
    "female_536.wav": [
        1.0,
        1.0,
        0.9944883584976196
    ],
    "male_160.wav": [
        0.0,
        0.0,
        0.022813471034169197
    ],
    "male_2066.wav": [
        0.0,
        0.0,
        0.003412258578464389
    ],
    "male_396.wav": [
        0.0,
        0.0,
        0.00024129053053911775
    ],
    "male_1070.wav": [
        0.0,
        0.0,
        0.0031572221778333187
    ],
    "female_1645.wav": [
        1.0,
        1.0,
        0.9549484252929688
    ],
    "male_1816.wav": [
        0.0,
        0.0,
        5.5956441258331324e-08
    ],
    "male_1037.wav": [
        0.0,
        0.0,
        0.014273055829107761
    ],
    "male_2288.wav": [
        0.0,
        0.0,
        0.01399963814765215
    ],
    "male_656.wav": [
        0.0,
        0.0,
        0.02046912908554077
    ],
    "male_1200.wav": [
        0.0,
        0.0,
        0.0029853370506316423
    ],
    "female_1431.wav": [
        0.0,
        1.0,
        0.2460232973098755
    ],
    "male_548.wav": [
        0.0,
        0.0,
        0.08489365130662918
    ],
    "female_442.wav": [
        1.0,
        1.0,
        0.7236926555633545
    ],
    "male_2344.wav": [
        1.0,
        0.0,
        0.7894101142883301
    ],
    "female_1061.wav": [
        1.0,
        1.0,
        0.9310021996498108
    ],
    "male_2941.wav": [
        0.0,
        0.0,
        0.0003649894497357309
    ],
    "female_785.wav": [
        1.0,
        1.0,
        0.8867856860160828
    ],
    "male_2337.wav": [
        0.0,
        0.0,
        0.25752589106559753
    ],
    "female_1735.wav": [
        1.0,
        1.0,
        0.8406991362571716
    ],
    "male_746.wav": [
        0.0,
        0.0,
        0.0015579144237563014
    ],
    "female_1120.wav": [
        0.0,
        1.0,
        0.3987636864185333
    ],
    "female_1732.wav": [
        1.0,
        1.0,
        0.9999159574508667
    ],
    "male_3351.wav": [
        0.0,
        0.0,
        7.372002073680051e-06
    ],
    "male_323.wav": [
        0.0,
        0.0,
        1.3407260439635138e-06
    ],
    "female_1591.wav": [
        1.0,
        1.0,
        0.999924898147583
    ],
    "female_1014.wav": [
        0.0,
        1.0,
        0.1653928905725479
    ],
    "female_1727.wav": [
        1.0,
        1.0,
        0.9252398014068604
    ],
    "male_3601.wav": [
        0.0,
        0.0,
        0.0014476899523288012
    ],
    "female_1577.wav": [
        0.0,
        1.0,
        0.10629148036241531
    ],
    "female_331.wav": [
        1.0,
        1.0,
        0.9970115423202515
    ],
    "female_65.wav": [
        1.0,
        1.0,
        0.9985744953155518
    ],
    "male_224.wav": [
        0.0,
        0.0,
        0.0466546006500721
    ],
    "male_2993.wav": [
        0.0,
        0.0,
        0.00048488142783753574
    ],
    "female_581.wav": [
        1.0,
        1.0,
        0.7978763580322266
    ],
    "female_1851.wav": [
        1.0,
        1.0,
        0.9503015279769897
    ],
    "male_572.wav": [
        1.0,
        0.0,
        0.5333442091941833
    ],
    "male_3586.wav": [
        0.0,
        0.0,
        1.808504202926997e-05
    ],
    "female_162.wav": [
        1.0,
        1.0,
        0.9837192893028259
    ],
    "female_2115.wav": [
        1.0,
        1.0,
        0.9155159592628479
    ],
    "male_1177.wav": [
        0.0,
        0.0,
        5.161041826795554e-06
    ],
    "male_2489.wav": [
        0.0,
        0.0,
        0.002700187498703599
    ],
    "female_783.wav": [
        1.0,
        1.0,
        0.940542995929718
    ],
    "male_51.wav": [
        0.0,
        0.0,
        0.0004514354222919792
    ],
    "male_2415.wav": [
        0.0,
        0.0,
        0.0006537417066283524
    ],
    "male_3400.wav": [
        0.0,
        0.0,
        0.0075597018003463745
    ],
    "male_3136.wav": [
        0.0,
        0.0,
        0.16008590161800385
    ],
    "female_2190.wav": [
        1.0,
        1.0,
        0.9998465776443481
    ],
    "male_2079.wav": [
        0.0,
        0.0,
        0.03627610206604004
    ],
    "male_3376.wav": [
        0.0,
        0.0,
        0.0001864229707280174
    ],
    "male_1076.wav": [
        0.0,
        0.0,
        0.017354624345898628
    ],
    "female_1610.wav": [
        1.0,
        1.0,
        0.9096161127090454
    ],
    "female_751.wav": [
        0.0,
        1.0,
        0.2992444932460785
    ],
    "female_541.wav": [
        1.0,
        1.0,
        0.9677957892417908
    ],
    "male_2816.wav": [
        0.0,
        0.0,
        0.0011095363879576325
    ],
    "male_3140.wav": [
        0.0,
        0.0,
        0.0013286472531035542
    ],
    "male_3202.wav": [
        1.0,
        0.0,
        0.9679686427116394
    ],
    "male_356.wav": [
        0.0,
        0.0,
        0.0016616287175565958
    ],
    "male_2252.wav": [
        0.0,
        0.0,
        1.9171817257301882e-05
    ],
    "male_439.wav": [
        0.0,
        0.0,
        0.0011986277531832457
    ],
    "male_1326.wav": [
        0.0,
        0.0,
        2.8742415452143177e-06
    ],
    "male_1374.wav": [
        0.0,
        0.0,
        1.0070694770547561e-05
    ],
    "male_2222.wav": [
        1.0,
        0.0,
        0.9048561453819275
    ],
    "male_1116.wav": [
        0.0,
        0.0,
        0.002801660681143403
    ],
    "male_3346.wav": [
        0.0,
        0.0,
        0.0010874210856854916
    ],
    "female_1077.wav": [
        1.0,
        1.0,
        0.6448299288749695
    ],
    "male_208.wav": [
        0.0,
        0.0,
        0.0005979374400340021
    ],
    "male_571.wav": [
        0.0,
        0.0,
        0.21799880266189575
    ],
    "male_3635.wav": [
        0.0,
        0.0,
        0.0003621951618697494
    ],
    "female_2248.wav": [
        1.0,
        1.0,
        0.9193587303161621
    ],
    "male_177.wav": [
        0.0,
        0.0,
        0.0023054094053804874
    ],
    "male_3008.wav": [
        0.0,
        0.0,
        0.006260117515921593
    ],
    "male_2575.wav": [
        0.0,
        0.0,
        9.286000567954034e-05
    ],
    "female_511.wav": [
        1.0,
        1.0,
        0.61993807554245
    ],
    "female_1521.wav": [
        1.0,
        1.0,
        0.9957108497619629
    ],
    "male_3403.wav": [
        0.0,
        0.0,
        0.03963197022676468
    ],
    "female_2272.wav": [
        1.0,
        1.0,
        0.8624873757362366
    ],
    "female_994.wav": [
        0.0,
        1.0,
        0.06777805835008621
    ],
    "male_517.wav": [
        0.0,
        0.0,
        4.7767392970854416e-05
    ],
    "female_1605.wav": [
        1.0,
        1.0,
        0.9391260147094727
    ],
    "male_2049.wav": [
        0.0,
        0.0,
        0.03320857137441635
    ],
    "female_115.wav": [
        1.0,
        1.0,
        0.721991777420044
    ],
    "male_2905.wav": [
        0.0,
        0.0,
        0.0007827373337931931
    ],
    "male_643.wav": [
        0.0,
        0.0,
        0.00010733226372394711
    ],
    "male_3331.wav": [
        0.0,
        0.0,
        0.0008550557540729642
    ],
    "female_1548.wav": [
        0.0,
        1.0,
        0.3146376609802246
    ],
    "female_85.wav": [
        1.0,
        1.0,
        0.5555270910263062
    ],
    "female_474.wav": [
        1.0,
        1.0,
        0.9669405817985535
    ],
    "female_1621.wav": [
        1.0,
        1.0,
        0.934410035610199
    ],
    "male_2789.wav": [
        0.0,
        0.0,
        1.5080216144269798e-05
    ],
    "male_498.wav": [
        0.0,
        0.0,
        0.0026425537653267384
    ],
    "female_508.wav": [
        1.0,
        1.0,
        0.9985698461532593
    ],
    "male_15.wav": [
        0.0,
        0.0,
        0.0009135263389907777
    ],
    "male_2539.wav": [
        0.0,
        0.0,
        0.000454096618341282
    ],
    "female_1625.wav": [
        1.0,
        1.0,
        0.9074950814247131
    ],
    "female_1142.wav": [
        1.0,
        1.0,
        0.9854336977005005
    ],
    "female_285.wav": [
        0.0,
        1.0,
        0.3398153483867645
    ],
    "male_140.wav": [
        0.0,
        0.0,
        0.021112263202667236
    ],
    "male_1764.wav": [
        0.0,
        0.0,
        0.1090124323964119
    ],
    "male_631.wav": [
        0.0,
        0.0,
        0.011048569343984127
    ],
    "female_57.wav": [
        1.0,
        1.0,
        0.9986786246299744
    ],
    "female_1703.wav": [
        1.0,
        1.0,
        0.9275047183036804
    ],
    "female_1717.wav": [
        1.0,
        1.0,
        0.9984769225120544
    ],
    "female_2183.wav": [
        1.0,
        1.0,
        0.6560649871826172
    ],
    "male_2747.wav": [
        0.0,
        0.0,
        1.879484079836402e-05
    ],
    "male_2630.wav": [
        0.0,
        0.0,
        0.004749590996652842
    ],
    "male_3347.wav": [
        0.0,
        0.0,
        0.006333877798169851
    ],
    "male_256.wav": [
        0.0,
        0.0,
        0.0028014385607093573
    ],
    "male_908.wav": [
        0.0,
        0.0,
        0.0033180711325258017
    ],
    "female_1410.wav": [
        1.0,
        1.0,
        0.5615400075912476
    ],
    "male_2678.wav": [
        0.0,
        0.0,
        0.0024383675772696733
    ],
    "male_3401.wav": [
        0.0,
        0.0,
        2.0096619834930607e-07
    ],
    "female_701.wav": [
        1.0,
        1.0,
        0.928474485874176
    ],
    "male_551.wav": [
        0.0,
        0.0,
        0.29268792271614075
    ],
    "male_629.wav": [
        0.0,
        0.0,
        0.004096624441444874
    ],
    "female_2303.wav": [
        1.0,
        1.0,
        0.9993441700935364
    ],
    "male_1082.wav": [
        0.0,
        0.0,
        0.00014662326429970562
    ],
    "female_845.wav": [
        1.0,
        1.0,
        0.9989742040634155
    ],
    "male_3164.wav": [
        0.0,
        0.0,
        0.008823314681649208
    ],
    "female_190.wav": [
        1.0,
        1.0,
        0.7404474020004272
    ],
    "female_504.wav": [
        1.0,
        1.0,
        0.9931521415710449
    ],
    "male_876.wav": [
        0.0,
        0.0,
        0.002905376721173525
    ],
    "male_1639.wav": [
        0.0,
        0.0,
        9.745782881509513e-05
    ],
    "male_2918.wav": [
        0.0,
        0.0,
        0.06296783685684204
    ],
    "male_196.wav": [
        0.0,
        0.0,
        0.001804065192118287
    ],
    "male_24.wav": [
        1.0,
        0.0,
        0.6510111689567566
    ],
    "male_2467.wav": [
        0.0,
        0.0,
        0.019499601796269417
    ],
    "female_456.wav": [
        1.0,
        1.0,
        0.9981416463851929
    ],
    "male_2081.wav": [
        0.0,
        0.0,
        7.803189873811789e-06
    ],
    "male_2011.wav": [
        0.0,
        0.0,
        0.06980438530445099
    ],
    "male_2034.wav": [
        0.0,
        0.0,
        0.00021432808716781437
    ],
    "female_1038.wav": [
        1.0,
        1.0,
        0.5261690616607666
    ],
    "male_3225.wav": [
        0.0,
        0.0,
        0.0023662105668336153
    ],
    "female_1691.wav": [
        1.0,
        1.0,
        0.9996792078018188
    ],
    "male_1383.wav": [
        0.0,
        0.0,
        0.01994721032679081
    ],
    "male_1198.wav": [
        0.0,
        0.0,
        0.0012945282505825162
    ],
    "male_928.wav": [
        0.0,
        0.0,
        0.00011179317516507581
    ],
    "male_336.wav": [
        0.0,
        0.0,
        0.0008847130229696631
    ],
    "male_2052.wav": [
        0.0,
        0.0,
        1.647773569857236e-05
    ],
    "female_1380.wav": [
        1.0,
        1.0,
        0.8576529026031494
    ],
    "female_1698.wav": [
        1.0,
        1.0,
        0.9661129713058472
    ],
    "female_1663.wav": [
        1.0,
        1.0,
        0.9917859435081482
    ],
    "female_1157.wav": [
        1.0,
        1.0,
        0.6739287376403809
    ],
    "female_101.wav": [
        1.0,
        1.0,
        0.996166467666626
    ],
    "male_538.wav": [
        0.0,
        0.0,
        0.01620340347290039
    ],
    "male_3615.wav": [
        0.0,
        0.0,
        0.00578240305185318
    ],
    "male_429.wav": [
        0.0,
        0.0,
        0.0009728969889692962
    ],
    "female_1105.wav": [
        1.0,
        1.0,
        0.710662305355072
    ],
    "male_3341.wav": [
        0.0,
        0.0,
        0.0006141695776022971
    ],
    "male_402.wav": [
        0.0,
        0.0,
        1.8323749827686697e-05
    ],
    "male_3263.wav": [
        0.0,
        0.0,
        0.007372379302978516
    ],
    "male_2278.wav": [
        0.0,
        0.0,
        0.006196160800755024
    ],
    "female_561.wav": [
        1.0,
        1.0,
        0.9327598810195923
    ],
    "female_935.wav": [
        1.0,
        1.0,
        0.9997593760490417
    ],
    "male_3562.wav": [
        0.0,
        0.0,
        0.00010906910756602883
    ],
    "male_1147.wav": [
        0.0,
        0.0,
        0.1808079183101654
    ],
    "male_3588.wav": [
        0.0,
        0.0,
        0.0002259137836517766
    ],
    "male_1678.wav": [
        0.0,
        0.0,
        0.0002877094375435263
    ],
    "male_2625.wav": [
        0.0,
        0.0,
        0.003827385837212205
    ],
    "male_2769.wav": [
        0.0,
        0.0,
        0.003508269554004073
    ],
    "male_3460.wav": [
        1.0,
        0.0,
        0.8118036389350891
    ],
    "female_1582.wav": [
        1.0,
        1.0,
        0.9993736147880554
    ],
    "female_2241.wav": [
        1.0,
        1.0,
        0.9968317151069641
    ],
    "male_1931.wav": [
        0.0,
        0.0,
        3.551541522028856e-05
    ],
    "female_2084.wav": [
        1.0,
        1.0,
        0.6203075051307678
    ],
    "male_3557.wav": [
        0.0,
        0.0,
        3.0136789064272307e-05
    ],
    "male_3014.wav": [
        0.0,
        0.0,
        5.008035805076361e-05
    ],
    "female_1152.wav": [
        0.0,
        1.0,
        0.09639698266983032
    ],
    "male_1573.wav": [
        0.0,
        0.0,
        0.014485107734799385
    ],
    "female_2112.wav": [
        1.0,
        1.0,
        0.8852013349533081
    ],
    "male_1921.wav": [
        0.0,
        0.0,
        0.0006343527347780764
    ],
    "female_1203.wav": [
        1.0,
        1.0,
        0.9995037317276001
    ],
    "male_3288.wav": [
        0.0,
        0.0,
        0.0076466770842671394
    ],
    "male_1680.wav": [
        0.0,
        0.0,
        0.014765464700758457
    ],
    "male_1651.wav": [
        0.0,
        0.0,
        5.134645775228819e-08
    ],
    "male_2044.wav": [
        0.0,
        0.0,
        0.00026718180743046105
    ],
    "male_3326.wav": [
        0.0,
        0.0,
        0.0025984772946685553
    ],
    "male_3208.wav": [
        0.0,
        0.0,
        0.0029525961726903915
    ],
    "male_2015.wav": [
        0.0,
        0.0,
        0.0001200632905238308
    ],
    "female_1111.wav": [
        1.0,
        1.0,
        0.9979216456413269
    ],
    "female_1784.wav": [
        1.0,
        1.0,
        0.8347025513648987
    ],
    "male_2599.wav": [
        0.0,
        0.0,
        4.623692439054139e-05
    ],
    "male_230.wav": [
        0.0,
        0.0,
        0.000142333417898044
    ],
    "male_2479.wav": [
        0.0,
        0.0,
        0.09214917570352554
    ],
    "male_207.wav": [
        0.0,
        0.0,
        2.4970613594632596e-06
    ],
    "female_1311.wav": [
        1.0,
        1.0,
        0.926341712474823
    ],
    "male_411.wav": [
        0.0,
        0.0,
        0.028392111882567406
    ],
    "female_801.wav": [
        1.0,
        1.0,
        0.999924898147583
    ],
    "female_2196.wav": [
        1.0,
        1.0,
        0.7412787079811096
    ],
    "female_1156.wav": [
        1.0,
        1.0,
        0.8286541700363159
    ],
    "male_3066.wav": [
        1.0,
        0.0,
        0.9580259919166565
    ],
    "male_940.wav": [
        0.0,
        0.0,
        4.409754910739139e-05
    ],
    "male_3178.wav": [
        0.0,
        0.0,
        0.00037040794268250465
    ],
    "male_1952.wav": [
        0.0,
        0.0,
        0.0004825483774766326
    ],
    "male_126.wav": [
        0.0,
        0.0,
        0.15298360586166382
    ],
    "female_1811.wav": [
        1.0,
        1.0,
        0.9958244562149048
    ],
    "male_1674.wav": [
        1.0,
        0.0,
        0.7323365807533264
    ],
    "male_2548.wav": [
        0.0,
        0.0,
        0.007570700254291296
    ],
    "female_1261.wav": [
        1.0,
        1.0,
        0.9965747594833374
    ],
    "male_2705.wav": [
        0.0,
        0.0,
        0.02955549769103527
    ],
    "female_212.wav": [
        1.0,
        1.0,
        0.9990850687026978
    ],
    "female_1955.wav": [
        1.0,
        1.0,
        0.9995044469833374
    ],
    "male_1721.wav": [
        0.0,
        0.0,
        5.3253945225151256e-05
    ],
    "male_2605.wav": [
        0.0,
        0.0,
        0.010529453866183758
    ],
    "male_3098.wav": [
        0.0,
        0.0,
        0.0002858524094335735
    ],
    "female_626.wav": [
        1.0,
        1.0,
        0.9633129239082336
    ],
    "male_1564.wav": [
        0.0,
        0.0,
        0.008703666739165783
    ],
    "male_344.wav": [
        0.0,
        0.0,
        0.000777462322730571
    ],
    "male_866.wav": [
        0.0,
        0.0,
        0.000397987081669271
    ],
    "male_3329.wav": [
        0.0,
        0.0,
        0.004320528358221054
    ],
    "male_1411.wav": [
        0.0,
        0.0,
        0.00021519468282349408
    ],
    "female_810.wav": [
        1.0,
        1.0,
        0.970992922782898
    ],
    "female_1444.wav": [
        0.0,
        1.0,
        0.004273279570043087
    ],
    "male_887.wav": [
        0.0,
        0.0,
        2.240633693872951e-05
    ],
    "female_486.wav": [
        0.0,
        1.0,
        0.09071967005729675
    ],
    "male_2766.wav": [
        0.0,
        0.0,
        0.4050600826740265
    ],
    "male_2699.wav": [
        0.0,
        0.0,
        0.000379679084289819
    ],
    "male_2285.wav": [
        0.0,
        0.0,
        0.00545482849702239
    ],
    "female_370.wav": [
        1.0,
        1.0,
        0.8366466760635376
    ],
    "male_3495.wav": [
        0.0,
        0.0,
        0.1169181540608406
    ],
    "male_1205.wav": [
        0.0,
        0.0,
        0.00010949260467896238
    ],
    "male_1335.wav": [
        0.0,
        0.0,
        0.0005165173788554966
    ],
    "female_1414.wav": [
        1.0,
        1.0,
        0.9083760976791382
    ],
    "male_1490.wav": [
        0.0,
        0.0,
        0.016153281554579735
    ],
    "female_1813.wav": [
        1.0,
        1.0,
        0.9559361338615417
    ],
    "female_1125.wav": [
        1.0,
        1.0,
        0.8744149208068848
    ],
    "female_1177.wav": [
        1.0,
        1.0,
        0.9481104016304016
    ],
    "male_3269.wav": [
        0.0,
        0.0,
        0.005119083449244499
    ],
    "female_499.wav": [
        1.0,
        1.0,
        0.9454319477081299
    ],
    "female_1740.wav": [
        1.0,
        1.0,
        0.9997263550758362
    ],
    "male_3079.wav": [
        0.0,
        0.0,
        0.0007834063144400716
    ],
    "female_1144.wav": [
        1.0,
        1.0,
        0.9709247350692749
    ],
    "male_3399.wav": [
        0.0,
        0.0,
        0.00043921550968661904
    ],
    "male_1762.wav": [
        0.0,
        0.0,
        0.015337525866925716
    ],
    "male_1305.wav": [
        0.0,
        0.0,
        0.0020187150221318007
    ],
    "male_2756.wav": [
        0.0,
        0.0,
        0.021553754806518555
    ],
    "male_162.wav": [
        0.0,
        0.0,
        0.00044661431456916034
    ],
    "male_1790.wav": [
        0.0,
        0.0,
        0.0011377930641174316
    ],
    "female_818.wav": [
        1.0,
        1.0,
        0.9954773783683777
    ],
    "male_240.wav": [
        0.0,
        0.0,
        0.06266416609287262
    ],
    "male_3185.wav": [
        0.0,
        0.0,
        1.5627998664058396e-06
    ],
    "female_324.wav": [
        1.0,
        1.0,
        0.9592121839523315
    ],
    "female_2219.wav": [
        1.0,
        1.0,
        0.973783016204834
    ],
    "male_2689.wav": [
        0.0,
        0.0,
        0.00023179822892416269
    ],
    "male_3226.wav": [
        0.0,
        0.0,
        0.019352979958057404
    ],
    "male_1159.wav": [
        0.0,
        0.0,
        0.0027928370982408524
    ],
    "male_130.wav": [
        0.0,
        0.0,
        0.0017134282970800996
    ],
    "male_3083.wav": [
        0.0,
        0.0,
        0.0003579191688913852
    ],
    "male_792.wav": [
        0.0,
        0.0,
        2.4325236154254526e-05
    ],
    "female_710.wav": [
        1.0,
        1.0,
        0.9987209439277649
    ],
    "male_2603.wav": [
        0.0,
        0.0,
        0.022307880222797394
    ],
    "female_410.wav": [
        1.0,
        1.0,
        0.7698392868041992
    ],
    "male_3138.wav": [
        0.0,
        0.0,
        0.00136245833709836
    ],
    "male_1427.wav": [
        0.0,
        0.0,
        0.001262614969164133
    ],
    "male_1362.wav": [
        0.0,
        0.0,
        0.00045586744090542197
    ],
    "male_2836.wav": [
        0.0,
        0.0,
        0.00013412284897640347
    ],
    "male_3452.wav": [
        0.0,
        0.0,
        0.00011377044575056061
    ],
    "female_1484.wav": [
        0.0,
        1.0,
        0.36455419659614563
    ],
    "female_26.wav": [
        1.0,
        1.0,
        0.9968627691268921
    ],
    "female_1005.wav": [
        1.0,
        1.0,
        0.9480857849121094
    ],
    "female_999.wav": [
        1.0,
        1.0,
        0.9775863885879517
    ],
    "female_2008.wav": [
        1.0,
        1.0,
        0.6215178370475769
    ],
    "male_286.wav": [
        0.0,
        0.0,
        0.00036512172664515674
    ],
    "male_421.wav": [
        0.0,
        0.0,
        0.004865131340920925
    ],
    "female_1496.wav": [
        1.0,
        1.0,
        0.9947463274002075
    ],
    "male_1778.wav": [
        0.0,
        0.0,
        0.0002745221718214452
    ],
    "male_576.wav": [
        0.0,
        0.0,
        0.00037640350637957454
    ],
    "male_1316.wav": [
        0.0,
        0.0,
        0.003428067546337843
    ],
    "male_92.wav": [
        0.0,
        0.0,
        0.004716634284704924
    ],
    "male_1511.wav": [
        0.0,
        0.0,
        0.02519829384982586
    ],
    "female_477.wav": [
        0.0,
        1.0,
        0.038298048079013824
    ],
    "female_1369.wav": [
        1.0,
        1.0,
        0.9883413910865784
    ],
    "female_1637.wav": [
        1.0,
        1.0,
        0.9772900342941284
    ],
    "male_3518.wav": [
        0.0,
        0.0,
        0.0006212512962520123
    ],
    "female_1552.wav": [
        1.0,
        1.0,
        0.971301794052124
    ],
    "male_2640.wav": [
        0.0,
        0.0,
        0.02714494988322258
    ],
    "female_1934.wav": [
        1.0,
        1.0,
        0.9961023330688477
    ],
    "male_2064.wav": [
        0.0,
        0.0,
        2.5186238417518325e-05
    ],
    "male_3455.wav": [
        0.0,
        0.0,
        3.738331599834055e-08
    ],
    "male_1965.wav": [
        0.0,
        0.0,
        0.004200081340968609
    ],
    "female_1950.wav": [
        0.0,
        1.0,
        0.0010516829788684845
    ],
    "male_947.wav": [
        0.0,
        0.0,
        0.00023514412168879062
    ],
    "female_2244.wav": [
        1.0,
        1.0,
        0.9971453547477722
    ],
    "female_641.wav": [
        1.0,
        1.0,
        0.7200201153755188
    ],
    "female_1980.wav": [
        1.0,
        1.0,
        0.9634637236595154
    ],
    "male_3539.wav": [
        0.0,
        0.0,
        0.005300300661474466
    ],
    "male_2525.wav": [
        0.0,
        0.0,
        0.0010860487818717957
    ],
    "male_2402.wav": [
        0.0,
        0.0,
        0.02482195943593979
    ],
    "female_693.wav": [
        1.0,
        1.0,
        0.7578485608100891
    ],
    "female_589.wav": [
        1.0,
        1.0,
        0.941310703754425
    ],
    "female_1275.wav": [
        1.0,
        1.0,
        0.9999339580535889
    ],
    "female_120.wav": [
        1.0,
        1.0,
        0.9703760743141174
    ],
    "male_1279.wav": [
        0.0,
        0.0,
        0.008422287181019783
    ],
    "male_1130.wav": [
        0.0,
        0.0,
        8.573142986278981e-05
    ],
    "male_1126.wav": [
        0.0,
        0.0,
        0.0029194660019129515
    ],
    "female_1048.wav": [
        1.0,
        1.0,
        0.9185682535171509
    ],
    "male_826.wav": [
        0.0,
        0.0,
        0.00277347001247108
    ],
    "male_2986.wav": [
        0.0,
        0.0,
        0.012892642989754677
    ],
    "female_827.wav": [
        1.0,
        1.0,
        0.9932281374931335
    ],
    "female_635.wav": [
        0.0,
        1.0,
        0.44864797592163086
    ],
    "female_2099.wav": [
        1.0,
        1.0,
        0.985314130783081
    ],
    "male_650.wav": [
        0.0,
        0.0,
        5.1942803111160174e-05
    ],
    "female_1799.wav": [
        1.0,
        1.0,
        0.9809156060218811
    ],
    "male_211.wav": [
        0.0,
        0.0,
        0.0015601164195686579
    ],
    "female_2031.wav": [
        1.0,
        1.0,
        0.9983975291252136
    ],
    "male_284.wav": [
        0.0,
        0.0,
        0.0007135412888601422
    ],
    "female_1402.wav": [
        1.0,
        1.0,
        0.905523955821991
    ],
    "female_1147.wav": [
        1.0,
        1.0,
        0.6632764935493469
    ],
    "male_1663.wav": [
        0.0,
        0.0,
        0.000762159179430455
    ],
    "male_2171.wav": [
        0.0,
        0.0,
        0.002062140963971615
    ],
    "female_1088.wav": [
        1.0,
        1.0,
        0.9995794892311096
    ],
    "male_2596.wav": [
        0.0,
        0.0,
        0.06479745358228683
    ],
    "male_2736.wav": [
        0.0,
        0.0,
        2.642418728271423e-08
    ],
    "male_3551.wav": [
        0.0,
        0.0,
        4.283062935428461e-06
    ],
    "male_377.wav": [
        0.0,
        0.0,
        3.7121477362234145e-05
    ],
    "female_344.wav": [
        1.0,
        1.0,
        0.7783167958259583
    ],
    "male_330.wav": [
        0.0,
        0.0,
        0.007901768200099468
    ],
    "male_897.wav": [
        0.0,
        0.0,
        0.009362447075545788
    ],
    "female_245.wav": [
        1.0,
        1.0,
        0.9871166348457336
    ],
    "male_276.wav": [
        0.0,
        0.0,
        0.005351927597075701
    ],
    "male_858.wav": [
        0.0,
        0.0,
        0.0036783884279429913
    ],
    "male_461.wav": [
        0.0,
        0.0,
        7.578669851682207e-07
    ],
    "male_3050.wav": [
        0.0,
        0.0,
        0.034093279391527176
    ],
    "male_568.wav": [
        0.0,
        0.0,
        0.018543699756264687
    ],
    "female_714.wav": [
        1.0,
        1.0,
        0.997209370136261
    ],
    "female_326.wav": [
        1.0,
        1.0,
        0.5870975852012634
    ],
    "female_168.wav": [
        1.0,
        1.0,
        0.6748778820037842
    ],
    "male_1829.wav": [
        0.0,
        0.0,
        0.013674510642886162
    ],
    "female_409.wav": [
        1.0,
        1.0,
        0.9997739195823669
    ],
    "female_591.wav": [
        1.0,
        1.0,
        0.8592064380645752
    ],
    "female_579.wav": [
        1.0,
        1.0,
        0.9993322491645813
    ],
    "male_2185.wav": [
        0.0,
        0.0,
        0.018922334536910057
    ],
    "male_448.wav": [
        0.0,
        0.0,
        0.0008766396204009652
    ],
    "male_332.wav": [
        0.0,
        0.0,
        8.948738104663789e-05
    ],
    "male_2753.wav": [
        0.0,
        0.0,
        0.02664465829730034
    ],
    "female_51.wav": [
        1.0,
        1.0,
        0.9884557723999023
    ],
    "female_1781.wav": [
        1.0,
        1.0,
        0.9614447355270386
    ],
    "female_2136.wav": [
        1.0,
        1.0,
        0.9999418258666992
    ],
    "male_3432.wav": [
        0.0,
        0.0,
        0.007368891034275293
    ],
    "male_1918.wav": [
        0.0,
        0.0,
        8.881738904165104e-05
    ],
    "male_2924.wav": [
        0.0,
        0.0,
        0.0031648101285099983
    ],
    "male_712.wav": [
        0.0,
        0.0,
        0.0018829824402928352
    ],
    "male_1739.wav": [
        0.0,
        0.0,
        0.00019012995471712202
    ],
    "male_1729.wav": [
        0.0,
        0.0,
        0.002931678667664528
    ],
    "female_1308.wav": [
        1.0,
        1.0,
        0.997894823551178
    ],
    "male_2972.wav": [
        0.0,
        0.0,
        0.00048731028800830245
    ],
    "female_114.wav": [
        1.0,
        1.0,
        0.9979152083396912
    ],
    "female_555.wav": [
        1.0,
        1.0,
        0.9441477060317993
    ],
    "male_1850.wav": [
        0.0,
        0.0,
        0.00038470374420285225
    ],
    "male_2846.wav": [
        0.0,
        0.0,
        1.7663686548985424e-06
    ],
    "female_152.wav": [
        1.0,
        1.0,
        0.5842234492301941
    ],
    "male_550.wav": [
        0.0,
        0.0,
        1.6020139810279943e-05
    ],
    "female_998.wav": [
        1.0,
        1.0,
        0.9964441657066345
    ],
    "male_636.wav": [
        0.0,
        0.0,
        0.025942130014300346
    ],
    "female_1084.wav": [
        1.0,
        1.0,
        0.961118221282959
    ],
    "male_1840.wav": [
        0.0,
        0.0,
        9.482533641858026e-05
    ],
    "male_726.wav": [
        0.0,
        0.0,
        0.00235933531075716
    ],
    "female_1273.wav": [
        1.0,
        1.0,
        0.8804574608802795
    ],
    "female_1227.wav": [
        1.0,
        1.0,
        0.9681460857391357
    ],
    "male_1505.wav": [
        0.0,
        0.0,
        2.0525394575088285e-06
    ],
    "male_977.wav": [
        0.0,
        0.0,
        0.00037895332206971943
    ],
    "male_2752.wav": [
        0.0,
        0.0,
        0.004811085760593414
    ],
    "male_3512.wav": [
        0.0,
        0.0,
        0.0005365642718970776
    ],
    "male_1117.wav": [
        0.0,
        0.0,
        0.1785847693681717
    ],
    "male_179.wav": [
        0.0,
        0.0,
        0.0029190497007220984
    ],
    "female_1429.wav": [
        0.0,
        1.0,
        0.11431699991226196
    ],
    "female_1003.wav": [
        1.0,
        1.0,
        0.9779726266860962
    ],
    "male_1184.wav": [
        0.0,
        0.0,
        1.5939765944494866e-05
    ],
    "male_1074.wav": [
        0.0,
        0.0,
        0.0016167223220691085
    ],
    "male_1358.wav": [
        0.0,
        0.0,
        0.011912423186004162
    ],
    "male_249.wav": [
        0.0,
        0.0,
        0.004988876171410084
    ],
    "male_2463.wav": [
        0.0,
        0.0,
        0.00535197276622057
    ],
    "female_1505.wav": [
        1.0,
        1.0,
        0.9988443851470947
    ],
    "male_566.wav": [
        0.0,
        0.0,
        0.004357695579528809
    ],
    "male_48.wav": [
        0.0,
        0.0,
        0.47273367643356323
    ],
    "male_3241.wav": [
        0.0,
        0.0,
        0.00033616588916629553
    ],
    "male_1758.wav": [
        1.0,
        0.0,
        0.9970090985298157
    ],
    "female_266.wav": [
        1.0,
        1.0,
        0.9903064966201782
    ],
    "male_2828.wav": [
        0.0,
        0.0,
        0.00010124041000381112
    ],
    "female_987.wav": [
        1.0,
        1.0,
        0.9672122597694397
    ],
    "female_1921.wav": [
        1.0,
        1.0,
        0.8317723274230957
    ],
    "female_1232.wav": [
        1.0,
        1.0,
        0.9526254534721375
    ],
    "female_1470.wav": [
        1.0,
        1.0,
        0.8488606214523315
    ],
    "female_185.wav": [
        1.0,
        1.0,
        0.7820243835449219
    ],
    "male_720.wav": [
        0.0,
        0.0,
        4.019280459033325e-05
    ],
    "male_2636.wav": [
        0.0,
        0.0,
        0.009131334722042084
    ],
    "male_2722.wav": [
        0.0,
        0.0,
        0.007450949866324663
    ],
    "male_879.wav": [
        0.0,
        0.0,
        0.03512311354279518
    ],
    "male_676.wav": [
        0.0,
        0.0,
        0.001507404027506709
    ],
    "male_787.wav": [
        0.0,
        0.0,
        0.00030850450275465846
    ],
    "male_2118.wav": [
        0.0,
        0.0,
        0.000681605190038681
    ],
    "male_2417.wav": [
        0.0,
        0.0,
        0.0003779793914873153
    ],
    "male_2262.wav": [
        0.0,
        0.0,
        0.0014570796629413962
    ],
    "female_1718.wav": [
        1.0,
        1.0,
        0.8786606788635254
    ],
    "male_2272.wav": [
        0.0,
        0.0,
        0.061913516372442245
    ],
    "male_3369.wav": [
        0.0,
        0.0,
        0.00036949929199181497
    ],
    "male_2383.wav": [
        0.0,
        0.0,
        0.0005559619748964906
    ],
    "male_2291.wav": [
        0.0,
        0.0,
        0.06710473448038101
    ],
    "male_3035.wav": [
        0.0,
        0.0,
        0.01810372620820999
    ],
    "male_1487.wav": [
        0.0,
        0.0,
        0.0006989124231040478
    ],
    "female_1243.wav": [
        1.0,
        1.0,
        0.5081772208213806
    ],
    "female_636.wav": [
        1.0,
        1.0,
        0.9239967465400696
    ],
    "male_770.wav": [
        1.0,
        0.0,
        0.9984569549560547
    ],
    "female_864.wav": [
        1.0,
        1.0,
        0.9983808994293213
    ],
    "female_847.wav": [
        0.0,
        1.0,
        0.2890835404396057
    ],
    "male_111.wav": [
        0.0,
        0.0,
        5.745739528606464e-08
    ],
    "male_893.wav": [
        0.0,
        0.0,
        0.02214541658759117
    ],
    "male_2936.wav": [
        0.0,
        0.0,
        8.398570935241878e-05
    ],
    "male_560.wav": [
        0.0,
        0.0,
        0.0009911417728289962
    ],
    "male_989.wav": [
        0.0,
        0.0,
        0.1866641491651535
    ],
    "male_1818.wav": [
        0.0,
        0.0,
        7.429449055962323e-07
    ],
    "female_1207.wav": [
        0.0,
        1.0,
        0.09910131245851517
    ],
    "male_1325.wav": [
        0.0,
        0.0,
        0.015135525725781918
    ],
    "female_1161.wav": [
        1.0,
        1.0,
        0.9946708083152771
    ],
    "female_569.wav": [
        1.0,
        1.0,
        0.9038686752319336
    ],
    "female_2107.wav": [
        1.0,
        1.0,
        0.9584660530090332
    ],
    "male_3180.wav": [
        0.0,
        0.0,
        0.009261851198971272
    ],
    "male_2969.wav": [
        0.0,
        0.0,
        0.008288465440273285
    ],
    "male_1004.wav": [
        0.0,
        0.0,
        0.001353961881250143
    ],
    "female_290.wav": [
        1.0,
        1.0,
        0.9754282832145691
    ],
    "male_271.wav": [
        0.0,
        0.0,
        0.1288953274488449
    ],
    "male_3236.wav": [
        0.0,
        0.0,
        0.00205266778357327
    ],
    "female_816.wav": [
        1.0,
        1.0,
        0.9657716155052185
    ],
    "female_1006.wav": [
        1.0,
        1.0,
        0.9998821020126343
    ],
    "male_2522.wav": [
        0.0,
        0.0,
        3.9802034734748304e-05
    ],
    "female_60.wav": [
        0.0,
        1.0,
        0.08687944710254669
    ],
    "female_963.wav": [
        1.0,
        1.0,
        0.9835838675498962
    ],
    "male_762.wav": [
        0.0,
        0.0,
        0.03227990120649338
    ],
    "male_1029.wav": [
        0.0,
        0.0,
        1.347090528724948e-05
    ],
    "male_2247.wav": [
        0.0,
        0.0,
        6.306807449618645e-07
    ],
    "male_3603.wav": [
        0.0,
        0.0,
        0.0009249789291061461
    ],
    "female_500.wav": [
        1.0,
        1.0,
        0.9981800317764282
    ],
    "female_1911.wav": [
        1.0,
        1.0,
        0.9252127408981323
    ],
    "male_3319.wav": [
        0.0,
        0.0,
        3.320269752293825e-05
    ],
    "female_584.wav": [
        1.0,
        1.0,
        0.9546597003936768
    ],
    "male_1189.wav": [
        0.0,
        0.0,
        2.075160045933444e-05
    ],
    "female_1846.wav": [
        1.0,
        1.0,
        0.9795089960098267
    ],
    "male_2557.wav": [
        0.0,
        0.0,
        0.00017033774929586798
    ],
    "female_1939.wav": [
        0.0,
        1.0,
        0.45190179347991943
    ],
    "male_3289.wav": [
        0.0,
        0.0,
        0.06260952353477478
    ],
    "female_2232.wav": [
        0.0,
        1.0,
        0.179162859916687
    ],
    "male_3297.wav": [
        0.0,
        0.0,
        0.14087998867034912
    ],
    "male_1847.wav": [
        0.0,
        0.0,
        0.0013831114629283547
    ],
    "male_2985.wav": [
        0.0,
        0.0,
        0.018943825736641884
    ],
    "female_1218.wav": [
        0.0,
        1.0,
        0.28846970200538635
    ],
    "male_2615.wav": [
        0.0,
        0.0,
        0.010572952218353748
    ],
    "male_1629.wav": [
        0.0,
        0.0,
        0.04103292152285576
    ],
    "male_216.wav": [
        0.0,
        0.0,
        0.010027994401752949
    ],
    "female_1035.wav": [
        1.0,
        1.0,
        0.7204347848892212
    ],
    "male_3082.wav": [
        0.0,
        0.0,
        0.0017172308871522546
    ],
    "male_3290.wav": [
        0.0,
        0.0,
        0.0017460919916629791
    ],
    "male_464.wav": [
        0.0,
        0.0,
        0.0012215134920552373
    ],
    "male_213.wav": [
        0.0,
        0.0,
        4.150919266976416e-06
    ],
    "male_7.wav": [
        0.0,
        0.0,
        0.21940378844738007
    ],
    "male_829.wav": [
        0.0,
        0.0,
        0.01995401456952095
    ],
    "male_1656.wav": [
        0.0,
        0.0,
        0.004668701905757189
    ],
    "male_1295.wav": [
        0.0,
        0.0,
        2.5964189262595028e-05
    ],
    "male_384.wav": [
        0.0,
        0.0,
        0.002489181701093912
    ],
    "male_3244.wav": [
        1.0,
        0.0,
        0.9961477518081665
    ],
    "male_3038.wav": [
        0.0,
        0.0,
        1.1618650205491576e-05
    ],
    "male_373.wav": [
        0.0,
        0.0,
        6.1006991018075496e-05
    ],
    "male_705.wav": [
        0.0,
        0.0,
        0.0037048356607556343
    ],
    "male_754.wav": [
        0.0,
        0.0,
        0.00021683763770852238
    ],
    "male_305.wav": [
        0.0,
        0.0,
        0.006526248529553413
    ],
    "male_433.wav": [
        0.0,
        0.0,
        0.00022638989321421832
    ],
    "female_1729.wav": [
        1.0,
        1.0,
        0.6677886843681335
    ],
    "male_3308.wav": [
        0.0,
        0.0,
        0.002007516101002693
    ],
    "female_1968.wav": [
        1.0,
        1.0,
        0.9959683418273926
    ],
    "male_1694.wav": [
        0.0,
        0.0,
        2.9176751922932453e-05
    ],
    "female_1183.wav": [
        1.0,
        1.0,
        0.9770057797431946
    ],
    "male_549.wav": [
        0.0,
        0.0,
        0.0006374776130542159
    ],
    "male_1671.wav": [
        0.0,
        0.0,
        0.00013777556887362152
    ],
    "female_2274.wav": [
        1.0,
        1.0,
        0.9568397998809814
    ],
    "male_3387.wav": [
        0.0,
        0.0,
        0.000342669925885275
    ],
    "male_790.wav": [
        0.0,
        0.0,
        0.000707569473888725
    ],
    "female_23.wav": [
        1.0,
        1.0,
        0.6803725361824036
    ],
    "male_3175.wav": [
        0.0,
        0.0,
        0.04063020274043083
    ],
    "male_1246.wav": [
        0.0,
        0.0,
        3.259826542034716e-07
    ],
    "male_1809.wav": [
        0.0,
        0.0,
        0.005784372333437204
    ],
    "male_3273.wav": [
        0.0,
        0.0,
        0.00011656878632493317
    ],
    "male_2586.wav": [
        0.0,
        0.0,
        0.00039237941382452846
    ],
    "male_2832.wav": [
        0.0,
        0.0,
        0.000763923570048064
    ],
    "male_2565.wav": [
        0.0,
        0.0,
        0.006024627014994621
    ],
    "female_1212.wav": [
        1.0,
        1.0,
        0.9985722303390503
    ],
    "male_872.wav": [
        0.0,
        0.0,
        0.00834962073713541
    ],
    "male_1606.wav": [
        0.0,
        0.0,
        0.012739099562168121
    ],
    "female_797.wav": [
        1.0,
        1.0,
        0.9988021850585938
    ],
    "male_2981.wav": [
        0.0,
        0.0,
        0.008959941565990448
    ],
    "male_2567.wav": [
        0.0,
        0.0,
        0.021580111235380173
    ],
    "male_3546.wav": [
        0.0,
        0.0,
        0.0069127753376960754
    ],
    "female_1601.wav": [
        1.0,
        1.0,
        0.9724533557891846
    ],
    "male_1686.wav": [
        0.0,
        0.0,
        0.030089328065514565
    ],
    "female_933.wav": [
        1.0,
        1.0,
        0.9971475005149841
    ],
    "female_1767.wav": [
        1.0,
        1.0,
        0.9062172174453735
    ],
    "male_1216.wav": [
        0.0,
        0.0,
        0.07490416616201401
    ],
    "female_419.wav": [
        0.0,
        1.0,
        0.4785536527633667
    ],
    "male_1095.wav": [
        0.0,
        0.0,
        0.012674189172685146
    ],
    "female_1434.wav": [
        1.0,
        1.0,
        0.8526216149330139
    ],
    "female_1761.wav": [
        1.0,
        1.0,
        0.5718424916267395
    ],
    "male_1274.wav": [
        0.0,
        0.0,
        0.00011691064719343558
    ],
    "male_3070.wav": [
        0.0,
        0.0,
        0.2901674807071686
    ],
    "male_1444.wav": [
        0.0,
        0.0,
        0.0003349574108142406
    ],
    "male_2928.wav": [
        0.0,
        0.0,
        0.00021209372789599001
    ],
    "male_1291.wav": [
        0.0,
        0.0,
        0.000508042227011174
    ],
    "female_640.wav": [
        1.0,
        1.0,
        0.8950232267379761
    ],
    "female_1894.wav": [
        1.0,
        1.0,
        0.9884545803070068
    ],
    "male_869.wav": [
        0.0,
        0.0,
        7.266300485753163e-07
    ],
    "female_1195.wav": [
        1.0,
        1.0,
        0.9912388920783997
    ],
    "female_1378.wav": [
        1.0,
        1.0,
        0.9978578686714172
    ],
    "male_2217.wav": [
        0.0,
        0.0,
        0.004542291630059481
    ],
    "female_236.wav": [
        1.0,
        1.0,
        0.9786351323127747
    ],
    "male_1359.wav": [
        0.0,
        0.0,
        1.2530664207588416e-05
    ],
    "female_759.wav": [
        1.0,
        1.0,
        0.9571278095245361
    ],
    "male_598.wav": [
        0.0,
        0.0,
        0.001234338735230267
    ],
    "female_732.wav": [
        1.0,
        1.0,
        0.9933144450187683
    ],
    "male_1436.wav": [
        0.0,
        0.0,
        0.00013991304149385542
    ],
    "male_1481.wav": [
        0.0,
        0.0,
        0.00016870631952770054
    ],
    "female_728.wav": [
        1.0,
        1.0,
        0.9987209439277649
    ],
    "male_359.wav": [
        0.0,
        0.0,
        4.456167152966373e-05
    ],
    "male_315.wav": [
        0.0,
        0.0,
        0.004158652387559414
    ],
    "female_923.wav": [
        0.0,
        1.0,
        0.27653881907463074
    ],
    "female_1858.wav": [
        1.0,
        1.0,
        0.9985515475273132
    ],
    "male_1493.wav": [
        0.0,
        0.0,
        1.0603881491988432e-05
    ],
    "male_3105.wav": [
        0.0,
        0.0,
        0.01283941138535738
    ],
    "male_907.wav": [
        0.0,
        0.0,
        0.0014139572158455849
    ],
    "male_3114.wav": [
        0.0,
        0.0,
        0.04836559295654297
    ],
    "male_798.wav": [
        0.0,
        0.0,
        0.01418212242424488
    ],
    "female_2305.wav": [
        1.0,
        1.0,
        0.8450289368629456
    ],
    "male_1870.wav": [
        0.0,
        0.0,
        0.00027978146681562066
    ],
    "male_587.wav": [
        0.0,
        0.0,
        0.0013482164358720183
    ],
    "female_1295.wav": [
        1.0,
        1.0,
        0.9390901923179626
    ],
    "male_1727.wav": [
        0.0,
        0.0,
        0.0043267132714390755
    ],
    "female_1205.wav": [
        1.0,
        1.0,
        0.9936477541923523
    ],
    "female_985.wav": [
        1.0,
        1.0,
        0.9637705683708191
    ],
    "female_1624.wav": [
        1.0,
        1.0,
        0.9115800857543945
    ],
    "male_2325.wav": [
        0.0,
        0.0,
        3.135668009690562e-07
    ],
    "male_2700.wav": [
        0.0,
        0.0,
        0.0033793782349675894
    ],
    "male_53.wav": [
        0.0,
        0.0,
        0.0021012471988797188
    ],
    "male_3199.wav": [
        0.0,
        0.0,
        1.608532329555601e-05
    ],
    "female_730.wav": [
        1.0,
        1.0,
        0.9981594681739807
    ],
    "female_467.wav": [
        1.0,
        1.0,
        0.6590495705604553
    ],
    "male_2929.wav": [
        0.0,
        0.0,
        2.7050979042542167e-05
    ],
    "male_2974.wav": [
        0.0,
        0.0,
        0.26829850673675537
    ],
    "male_3064.wav": [
        0.0,
        0.0,
        0.023511318489909172
    ],
    "male_297.wav": [
        0.0,
        0.0,
        0.08957237750291824
    ],
    "male_619.wav": [
        0.0,
        0.0,
        1.2960587980614946e-07
    ],
    "female_566.wav": [
        1.0,
        1.0,
        0.9992013573646545
    ],
    "male_264.wav": [
        0.0,
        0.0,
        0.26819542050361633
    ],
    "male_174.wav": [
        0.0,
        0.0,
        0.005227222107350826
    ]
}